packagesinpython2/__init__.py
packagesinpython2-0.0.1.dist-info/METADATA
packagesinpython2-0.0.1.dist-info/WHEEL
packagesinpython2-0.0.1.dist-info/license.txt
packagesinpython2-0.0.1.dist-info/top_level.txt
packagesinpython2-0.0.1.dist-info/RECORD
