Metadata-Version: 2.1
Name: packagesinpython2
Version: 0.0.1
Summary: adding number
Home-page: https://github.com/AkashKumarGit/Insurance_Fraud
Author: chaitanya Kumar
Author-email: chaitanyakumar10aug@gmail.com
License: UNKNOWN
Platform: UNKNOWN
Classifier: Programming Language :: Python :: 3
Classifier: License :: OSI Approved :: MIT License
Classifier: Operating System :: OS Independent
